rpyc_mem/__init__.py
rpyc_mem/_version.py
rpyc_mem/errors.py
rpyc_mem/client/__init__.py
rpyc_mem/client/remote_module.py
rpyc_mem/client/rpyc_mem_object.py
rpyc_mem/connect/__init__.py
rpyc_mem/connect/rpyc_mem_connect.py
rpyc_mem/service/__init__.py
rpyc_mem/service/rpyc_mem_service.py
rpyc_mem/session/__init__.py
rpyc_mem/session/rpyc_mem_session.py
rpyc_mem/utils/__init__.py
rpyc_mem/utils/object_proxy.py
rpyc_mem-1.0.1.dist-info/AUTHORS.md
rpyc_mem-1.0.1.dist-info/LICENSE
rpyc_mem-1.0.1.dist-info/METADATA
rpyc_mem-1.0.1.dist-info/WHEEL
rpyc_mem-1.0.1.dist-info/top_level.txt
rpyc_mem-1.0.1.dist-info/RECORD
