Metadata-Version: 2.1
Name: rpyc-mem
Version: 1.0.1
Summary: 'A light weight RPyC based shared memory for Python'
Home-page: https://github.com/m0hithreddy/rpyc-mem
Author: Mohith Reddy
Author-email: dev.m0hithreddy@gmail.com
License: UNKNOWN
Project-URL: Bug Tracker, https://github.com/m0hithreddy/rpyc-mem/issues
Platform: UNKNOWN
Classifier: Development Status :: 4 - Beta
Classifier: License :: OSI Approved :: MIT License
Classifier: Operating System :: OS Independent
Classifier: Programming Language :: Python
Classifier: Programming Language :: Python :: 2
Classifier: Programming Language :: Python :: 2.7
Classifier: Programming Language :: Python :: 3
Classifier: Programming Language :: Python :: 3.0
Classifier: Programming Language :: Python :: 3.1
Classifier: Programming Language :: Python :: 3.2
Classifier: Programming Language :: Python :: 3.3
Classifier: Programming Language :: Python :: 3.4
Classifier: Programming Language :: Python :: 3.5
Classifier: Programming Language :: Python :: 3.6
Classifier: Programming Language :: Python :: 3.7
Classifier: Topic :: System :: Distributed Computing
License-File: LICENSE
License-File: AUTHORS.md
Requires-Dist: rpyc (<6.0.0,>=5.0.0)
